toomanyplugins/__init__.py
toomanyplugins/excruciating_logger.py
toomanyplugins/plugin.py
toomanyplugins/toomanyobjects.py
toomanyplugins/toomanystubs.py
toomanyplugins-0.1.0.dist-info/METADATA
toomanyplugins-0.1.0.dist-info/WHEEL
toomanyplugins-0.1.0.dist-info/top_level.txt
toomanyplugins-0.1.0.dist-info/RECORD
