Metadata-Version: 2.4
Name: toomanyplugins
Version: 0.1.0
Summary: Python utilities for automatic stub generation, excruciating line-by-line logging, and dynamic plugin injection.
Author-email: Miles <you@example.com>
License: MIT
Keywords: logging,plugin,stub-generation,decorator
Classifier: Programming Language :: Python :: 3
Classifier: License :: OSI Approved :: MIT License
Classifier: Development Status :: 4 - Beta
Classifier: Intended Audience :: Developers
Classifier: Topic :: Software Development :: Libraries :: Python Modules
Requires-Python: >=3.8
Requires-Dist: loguru>=0.6.0
